mountains/__init__.py
mountains/base.py
mountains/concurrent/__init__.py
mountains/database/__init__.py
mountains/database/records.py
mountains/datetime/__init__.py
mountains/datetime/converter.py
mountains/decorator/__init__.py
mountains/django/__init__.py
mountains/django/api.py
mountains/django/model.py
mountains/django/utils.py
mountains/encoding/__init__.py
mountains/encoding/converter.py
mountains/file/__init__.py
mountains/file/csv.py
mountains/file/excel.py
mountains/gis/__init__.py
mountains/gis/evil_transform.py
mountains/http/__init__.py
mountains/http/data/mobile_ua.txt
mountains/http/data/user_agents.txt
mountains/json/__init__.py
mountains/logging/__init__.py
mountains/logging/terminal.py
mountains/logging/terminal_size.py
mountains/ssh/__init__.py
mountains/tornado/__init__.py
mountains/utils/__init__.py
mountains/utils/converter.py
mountains/utils/email.py
mountains/utils/string_utils.py
tests/__init__.py
tests/test_concurrent.py
tests/test_datetime.py
tests/test_encoding.py
tests/test_file.py
tests/test_http.py
tests/test_json.py
tests/test_logging.py
tests/test_string_utils.py
tests/test_utils.py
mountains-0.8.8.dist-info/LICENSE
mountains-0.8.8.dist-info/METADATA
mountains-0.8.8.dist-info/WHEEL
mountains-0.8.8.dist-info/top_level.txt
mountains-0.8.8.dist-info/zip-safe
mountains-0.8.8.dist-info/RECORD
